LICENSE
README.md
setup.py
propelauth_django_rest_framework/__init__.py
propelauth_django_rest_framework/auth_helpers.py
propelauth_django_rest_framework.egg-info/PKG-INFO
propelauth_django_rest_framework.egg-info/SOURCES.txt
propelauth_django_rest_framework.egg-info/dependency_links.txt
propelauth_django_rest_framework.egg-info/requires.txt
propelauth_django_rest_framework.egg-info/top_level.txt