Metadata-Version: 2.1
Name: propelauth-django-rest-framework
Version: 4.2.8
Summary: A library for managing authentication in Django Rest Framework
Home-page: https://github.com/propelauth/propelauth-django-rest-framework
Author: PropelAuth
Author-email: support@propelauth.com
License: MIT
Platform: UNKNOWN
License-File: LICENSE
